ddapm_test_agent/__init__.py
ddapm_test_agent/agent.py
ddapm_test_agent/apmtelemetry.py
ddapm_test_agent/checks.py
ddapm_test_agent/client.py
ddapm_test_agent/cmd.py
ddapm_test_agent/context.py
ddapm_test_agent/fmt.py
ddapm_test_agent/integration.py
ddapm_test_agent/logs.py
ddapm_test_agent/metrics.py
ddapm_test_agent/remoteconfig.py
ddapm_test_agent/trace.py
ddapm_test_agent/trace_checks.py
ddapm_test_agent/trace_snapshot.py
ddapm_test_agent/tracerflare.py
ddapm_test_agent/tracestats.py
ddapm_test_agent/tracestats_snapshot.py
ddapm_test_agent/vcr_proxy.py
ddapm_test_agent/web.py
ddapm_test_agent/static/style.css
ddapm_test_agent/templates/base.html
ddapm_test_agent/templates/config.html
ddapm_test_agent/templates/dashboard.html
ddapm_test_agent/templates/macros.html
ddapm_test_agent/templates/requests.html
ddapm_test_agent/templates/session_detail.html
ddapm_test_agent/templates/sessions.html
ddapm_test_agent/templates/snapshot_detail.html
ddapm_test_agent/templates/snapshots.html
ddapm_test_agent/templates/trace_detail.html
ddapm_test_agent/templates/tracer_flares.html
ddapm_test_agent/templates/traces.html
ddapm_test_agent-1.39.0.dist-info/licenses/LICENSE.BSD3
ddapm_test_agent-1.39.0.dist-info/licenses/LICENSE.apache2
ddapm_test_agent-1.39.0.dist-info/METADATA
ddapm_test_agent-1.39.0.dist-info/WHEEL
ddapm_test_agent-1.39.0.dist-info/entry_points.txt
ddapm_test_agent-1.39.0.dist-info/top_level.txt
ddapm_test_agent-1.39.0.dist-info/RECORD
