Metadata-Version: 2.4
Name: ddapm-test-agent
Version: 1.39.0
Summary: Test agent for Datadog APM client libraries
Home-page: https://github.com/Datadog/dd-apm-test-agent
Author: Kyle Verhoog
Author-email: kyle@verhoog.ca
License: BSD 3
Classifier: Programming Language :: Python
Classifier: Programming Language :: Python :: 3.11
Classifier: Programming Language :: Python :: 3.12
Classifier: Programming Language :: Python :: 3.13
Requires-Python: >=3.8
License-File: LICENSE.BSD3
License-File: LICENSE.apache2
Requires-Dist: aiohttp
Requires-Dist: ddsketch[serialization]
Requires-Dist: msgpack
Requires-Dist: requests
Requires-Dist: typing_extensions
Requires-Dist: yarl
Requires-Dist: requests-aws4auth
Requires-Dist: jinja2>=3.0.0
Requires-Dist: pyyaml
Requires-Dist: opentelemetry-proto<1.37.0,>1.33.0
Requires-Dist: protobuf>=3.19.0
Requires-Dist: grpcio<2.0,>=1.66.2
Requires-Dist: pywin32; sys_platform == "win32"
Provides-Extra: testing
Requires-Dist: ddtrace==3.15.0; extra == "testing"
Requires-Dist: pytest; extra == "testing"
Requires-Dist: riot==0.20.1; extra == "testing"
Requires-Dist: PyYAML==6.0.3; extra == "testing"
Dynamic: author
Dynamic: author-email
Dynamic: classifier
Dynamic: description
Dynamic: description-content-type
Dynamic: home-page
Dynamic: license
Dynamic: license-file
Dynamic: provides-extra
Dynamic: requires-dist
Dynamic: requires-python
Dynamic: summary
